async_sendgrid/__init__.py
async_sendgrid/sendgrid.py
async_sendgrid-0.0.4.dist-info/LICENSE
async_sendgrid-0.0.4.dist-info/METADATA
async_sendgrid-0.0.4.dist-info/WHEEL
async_sendgrid-0.0.4.dist-info/RECORD
